sboon_ai_tools/__init__.py
sboon_ai_tools/audio_utils/__init__.py
sboon_ai_tools/audio_utils/processor.py
sboon_ai_tools/datasets/__init__.py
sboon_ai_tools/datasets/loader.py
sboon_ai_tools/datasets/data/data_energy.csv
sboon_ai_tools/datasets/data/sample_data.csv
sboon_ai_tools/h5_manager/__init__.py
sboon_ai_tools/h5_manager/core.py
sboon_ai_tools-0.1.2.dist-info/licenses/LICENSE
sboon_ai_tools-0.1.2.dist-info/METADATA
sboon_ai_tools-0.1.2.dist-info/WHEEL
sboon_ai_tools-0.1.2.dist-info/top_level.txt
sboon_ai_tools-0.1.2.dist-info/RECORD
