Metadata-Version: 2.4
Name: sboon_ai_tools
Version: 0.1.2
Summary: Sboon Studio : AI Tools Library
Author: BOONNATEE SAKBOONYARAT
Author-email: boonnatee@gmail.com, boonnatee.sak@mwit.ac.th
License: MIT License
Project-URL: Homepage, https://git.mwit.ac.th/cs/sboon-tool-library/sboon-ai-studio
Project-URL: Bug Tracker, https://git.mwit.ac.th/cs/sboon-tool-library/sboon-ai-studio/-/issues
Requires-Python: >=3.7
License-File: LICENSE
Requires-Dist: h5py
Requires-Dist: matplotlib
Requires-Dist: numpy
Requires-Dist: pandas
Requires-Dist: requests
Dynamic: license-file
